ya_eureka_binder/__init__.py
ya_eureka_binder-0.1.0.dist-info/LICENSE
ya_eureka_binder-0.1.0.dist-info/WHEEL
ya_eureka_binder-0.1.0.dist-info/METADATA
ya_eureka_binder-0.1.0.dist-info/RECORD
