Metadata-Version: 2.1
Name: ya-eureka-binder
Version: 0.1.0
Summary: Client for Netflix Eureka
License: BSD
Author: Ivan Tyshchenko
Requires-Python: >=3.6,<4.0
Classifier: License :: Other/Proprietary License
Classifier: Programming Language :: Python :: 3
Classifier: Programming Language :: Python :: 3.6
Classifier: Programming Language :: Python :: 3.7
Classifier: Programming Language :: Python :: 3.8
Classifier: Programming Language :: Python :: 3.9
Requires-Dist: httpx (>=0.19.0,<0.20.0)
